setup.py
horse_forecastio/__init__.py
horse_forecastio/graphs.py
horse_forecastio.egg-info/PKG-INFO
horse_forecastio.egg-info/SOURCES.txt
horse_forecastio.egg-info/dependency_links.txt
horse_forecastio.egg-info/requires.txt
horse_forecastio.egg-info/top_level.txt