Metadata-Version: 1.1
Name: horse-forecastio
Version: 0.1.0
Summary: ForecastIO integration bridle for Horse
Home-page: https://github.com/grieve/horse-forecastio
Author: Ryan Grieve
Author-email: me@ryangrieve.com
License: MIT
Keywords: chatbot slack chat bot communication forecastio
Platform: UNKNOWN
Classifier: Development Status :: 3 - Alpha
Classifier: Intended Audience :: Developers
Classifier: Topic :: Communications :: Chat
Classifier: License :: OSI Approved :: MIT License
Classifier: Programming Language :: Python :: 2
Classifier: Programming Language :: Python :: 2.6
Classifier: Programming Language :: Python :: 2.7
Classifier: Programming Language :: Python :: 3
Classifier: Programming Language :: Python :: 3.2
Classifier: Programming Language :: Python :: 3.3
Classifier: Programming Language :: Python :: 3.4
